{
    "CC Template": {
        "prefix": "CCTemplate",
        "body": [
            "/*",
            "    Mahbubur Rahman",
            "    United International University",
            "*/",
            "#include <bits/stdc++.h>",
            "using namespace std;",
            "",
            "typedef long long ll;",
            "typedef vector<int> vi;",
            "",
            "#define nl cout << endl",
            "#define Yes printf(\"Yes\\n\")",
            "#define No printf(\"No\\n\")",
            "#define YES printf(\"YES\\n\")",
            "#define NO printf(\"NO\\n\")",
            "",
            "#define scan(x, s)              \\",
            "    for (int i = 0; i < s; i++) \\",
            "        cin >> x[i];",
            "#define scanV(x, s)             \\",
            "    for (int i = 0; i < s; i++) \\",
            "    {                           \\",
            "        int temp;               \\",
            "        cin >> temp;            \\",
            "        x.push_back(temp);      \\",
            "    }",
            "#define print(x)              \\",
            "    for (auto value : x)      \\",
            "        cout << value << \" \"; \\",
            "    cout << endl;",
            "",
            "void solve()",
            "{",
            "    $0",
            "}",
            "",
            "int main()",
            "{",
            "    solve();$2",
            "",
            "    return 0;",
            "}"
        ],
        "description": "CC Template"
    },
    "Cpp Template": {
        "prefix": "CppTemplate",
        "body": [
            "#include <bits/stdc++.h>",
            "using namespace std;",
            "",
            "int main()",
            "{",
            "    $0",
            "",
            "    return 0;",
            "}"
        ],
        "description": "C++ Template"
    },
    "Test Case": {
        "prefix": "testCase",
        "body": [
            "int t;",
            "cin >> t;",
            "while (t--)",
            "{",
            "    solve();$0",
            "}"
        ],
        "description": "Test Case"
    },
    "Ternary Operator": {
        "prefix": "Ternary Operator",
        "body": [
            "$1 ? cout << $2 : cout << $0;"
        ],
        "description": "Ternary Operator"
    },
    "Scan Array": {
        "prefix": "ScanArray",
        "body": [
            "int n;",
            "cin >> n;",
            "int arr[n];",
            "scan(arr, n);"
        ],
        "description": "Scan Array"
    },
    "Scan Vector": {
        "prefix": "ScanVector",
        "body": [
            "int n;",
            "cin >> n;",
            "vi v;",
            "scanv(v, n);"
        ],
        "description": "Scan Array"
    }
}